{
  "create_new_account": "Create New Account",
  "login": "Login",
  "username": "Username",
  "enter_username": "Enter username",
  "password": "Password",
  "enter_password": "Enter password",
  "mobile_number": "Mobile Number",
  "enter_mobile_number": "Enter mobile number",
  "agree_on": "I agree to",
  "agree_terms": "the Terms, Conditions, and Privacy Policy",
  "register": "Register",
  "already_have_account": "Already have an account?",
  "dont_have_account": "Don't have an account?",
  "app_name": "Kheet Amal",
  "welcome_title": "Welcome 👋",
  "welcome_subtitle": "Our app helps reunite missing children with their families",
  "search_title": "Search with us 🔍",
  "search_subtitle": "You can search for missing children or add a new report easily",
  "together_title": "Together we bring them back 🏠",
  "together_subtitle": "Join us and help bring a smile back to every home",
  "next_button": "Next",
  "get_started_button": "Get Started",
  "skip": "Skip",
  "forgot_password": "Forgot Password?",
  "enter_verification_code": "Enter Verification Code",
  "reset_password": "Reset Password",
  "enter_phone_number_msg": "Please enter your registered mobile number to send the verification code",
  "enter_verification_code_msg": "Please enter the verification code sent to your mobile number",
  "new_password_different": "The new password must be different from the previous one",
  "new_password": "New Password",
  "phone_number": "Phone Number",
  "enter_new_password": "Enter New Password",
  "country_code": "+20",
  "enter_phone_number": "Enter Phone Number",
  "timer": "1:00",
  "resend_code": "Resend Code",
  "confirm_new_password": "Confirm New Password",
  "enter_new_password_again": "Enter New Password Again",
  "confirm_code": "Confirm Code",
  "password_changed_success": "Password changed successfully!",
  "login_with_new_password": "You can now use the new password to log in securely",
  "send_code": "Send Code",
  "resend": "Resend",
  "did_not_receive_code": "Didn’t receive the code?",
  "confirm": "Confirm",
  "report_details": "Report Details",
    "ai_hint": "You can use artificial intelligence to imagine how the child might look in the past or future",
    "posted_by": "Posted by",
    "contact": "Contact",
    "child_full_name": "Ahmed Mohamed Ahmed Mohamed",
    "last_seen_place": "Last seen location:",
    "missing_date": "Date of disappearance:",
    "description": "Description:",
    "clothing_at_disappearance": "Clothing at time of disappearance:",
    "eye_color": "Eye color:",
    "skin_color": "Skin color:",
    "hair_color": "Hair color:",
    "special_marks": "Distinctive marks:", 
    "share": "Share",
  "password_reset_success": {
    "title": "Password Reset",
    "success_title": "Password changed successfully!",
    "success_description": "You can now use the new password to log in securely",
    "login_button": "Login",
     "user-not-found": "User not found",
  "wrong-password": "Incorrect password",
  "email-already-in-use": "This email is already in use",
  "weak-password": "Weak password",
  "invalid-email": "Invalid email format"
  
  },
  "required": "This field is required",
  "home": "Home",
  "search": "Search",
  "add": "Add Report",
  "profile": "Profile",
  "search_placeholder": "Search by child’s name or location...",
  "search_message_suffix": ", Every search brings a child closer to their family",
  "search_message_intro": "Type a name or location, or try quick filters",
  "latest_cases": "Latest cases",
  "change_governorate": "You can change the governorate or reduce details for more accurate results",
  "reset_filters": "Reset filters",
  "show_latest_cases": "Show latest cases",
  "add_report": {
    "add_report": "Add Report",
    "report_type": "Report Type",
    "missing_child": "Missing Child",
    "child_verification": "Child Needs Verification",
    "child_name": "Name",
    "enter_child_name": "Enter Child's Name",
    "gender": "Gender",
    "male": "Male",
    "female": "Female",
    "age": "Age",
    "years": "Years",
    "skin_color": "Skin Color",
    "select_skin_color": "Select Skin Color",
    "eye_color": "Eye Color",
    "select_eye_color": "Select Eye Color",
    "hair_color": "Hair Color",
    "select_hair_color": "Select Hair Color",
    "attach_recent_photo": "(Please attach a recent photo of the child) (Optional)",
    "optional": "(Optional)",
    "distinctive_marks": "Distinctive Marks",
    "attach_photo": "Attach Photo",
    "example_mark": "Example: Small scar above the eyebrow",
    "place": "Place",
    "enter_last_seen_place": "Enter Last Seen Location",
    "clothes_at_disappearance": "Clothes at Disappearance",
    "example_clothes": "Example: Blue t-shirt, jeans, and white sneakers",
    "last_seen_date": "(Select Last Seen Date)",
    "date": "Date",
    "day_month_year": "Day/Month/Year",
    "description": "Description",
    "enter_additional_details": "Enter any additional details to help clarify",
    "contact_number": "Contact Number",
    "first": "(First)",
    "enter_phone_number": "Enter Phone Number",
    "second": "(Second)",
    "send_report": "Send Report",
    "skin_color_light": "Light",
    "skin_color_wheat": "Wheat",
    "skin_color_tan": "Tan",
    "skin_color_dark": "Dark",
    "eye_color_blue": "Blue",
    "eye_color_black": "Black",
    "eye_color_brown": "Brown",
    "eye_color_green": "Green",
    "eye_color_gray": "Gray",
    "eye_color_hazel": "Hazel",
    "eye_color_amber": "Amber",
    "hair_color_black": "Black",
    "hair_color_brown": "Brown",
    "hair_color_blonde": "Blonde",
    "hair_color_red": "Red",
    "hair_color_gray": "Gray",
    "hair_color_white": "White"
  },
  "homeTitle": "Home",
  "statistics": "Statistics",
  "missingTab": "Missing",
  "suspectsTab": "Suspects",
  "missingBannerTitle": "Missing Children",
  "missingBannerDesc": "List of children reported missing, share with us to help find them faster.",
  "suspectsBannerTitle": "Children under suspicion",
  "suspectsBannerDesc": "Children may be in unsafe conditions, any help or information can help.",
  "name": "Name:",
  "age": "Age:",
  "gender": "Gender:",
  "place": "Place:",
  "since": "Since 3 days",
  "details": "Details",
  "summary": "Summary",
  "performance": "Performance",
  "response_time": "Average Response Time",
  "h":"h",
  "from_report_to_first_interaction": "From Report to First Interaction",
  "total_volunteers": "Total Volunteers",
  "active_users": "Active Users in App",
  "growth_since_last_month": "+15% from last month",
  "average_user_rating": "Average User Ratings",
  "app_rating": "App Rating",
  "user_activity_metrics": "User Activity Metrics",
  "network_performance": "Network Performance",
  "new_reports_today": "New Reports Today",
  "daily_views": "Daily Views",
  "interactions": "Interactions (Comments/Shares)",
  "active_usage_rate": "Active Usage Rate",
  "ai_feature_usage": "AI Feature Usage",
  "ai_statistics": "AI Statistics",
  "imagine_requests": "Imagine Requests",
  "matching_accuracy": "Matching Accuracy",
  "analyzed_images": "Analyzed Images",
  "face_recognition_success": "Face Recognition Success",
  "notifications": "Notifications",
  "no_notifications_title": "No notifications yet",
  "no_notifications_subtitle": "Stay tuned for new comments and nearby reports.",
  "my_account": "My Account",
  "saved": "Saved",
  "reports": "My Reports",
  "language": "Language",
  "settings": "Settings",
  "logout": "Logout",
  "edit_account": "Edit Account",
  "save_changes": "Save Changes",
  "save_success": "Changes Saved Successfully",
  "data_updated": "Your personal information has been updated",
  "email": "Email",
  "phone": "Phone Number",
  "location": "Location",
  "enter_name": "Please enter your name",
  "enter_email": "Please enter your email",
  "enter_phone": "Please enter your phone number",
  "updating": "Updating your information...",
  "bookmarks": "Bookmarks",
  "check": "You must accept the Terms and Conditions",
  "select_language": "Select Language",
  "english": "English",
  "arabic": "Arabic",
  "profile_updated": "Your personal information has been updated",
  "changes_saved": "Changes have been saved successfully"


}
